jlab_enhanced_launcher/__init__.py
jlab_enhanced_launcher/_version.py
jlab_enhanced_launcher-4.0.1.data/data/share/jupyter/labextensions/@jlab-enhanced/launcher/package.json
jlab_enhanced_launcher-4.0.1.data/data/share/jupyter/labextensions/@jlab-enhanced/launcher/schemas/@jlab-enhanced/launcher/package.json.orig
jlab_enhanced_launcher-4.0.1.data/data/share/jupyter/labextensions/@jlab-enhanced/launcher/schemas/@jlab-enhanced/launcher/plugin.json
jlab_enhanced_launcher-4.0.1.data/data/share/jupyter/labextensions/@jlab-enhanced/launcher/static/859.f47162317de4384762e7.js
jlab_enhanced_launcher-4.0.1.data/data/share/jupyter/labextensions/@jlab-enhanced/launcher/static/912.e59b5f08a56a18069774.js
jlab_enhanced_launcher-4.0.1.data/data/share/jupyter/labextensions/@jlab-enhanced/launcher/static/remoteEntry.d5d5d61346725adb3a89.js
jlab_enhanced_launcher-4.0.1.data/data/share/jupyter/labextensions/@jlab-enhanced/launcher/static/style.js
jlab_enhanced_launcher-4.0.1.data/data/share/jupyter/labextensions/@jlab-enhanced/launcher/static/third-party-licenses.json
jlab_enhanced_launcher-4.0.1.data/data/share/jupyter/labextensions/@jlab-enhanced/launcher/install.json
jlab_enhanced_launcher-4.0.1.dist-info/METADATA
jlab_enhanced_launcher-4.0.1.dist-info/WHEEL
jlab_enhanced_launcher-4.0.1.dist-info/licenses/LICENSE
jlab_enhanced_launcher-4.0.1.dist-info/RECORD
