Metadata-Version: 2.4
Name: jlab_enhanced_launcher
Version: 4.0.1
Summary: A enhanced launcher for JupyterLab
Project-URL: Homepage, https://github.com/jupyterlab-contrib/jlab-enhanced-launcher
Project-URL: Bug Tracker, https://github.com/jupyterlab-contrib/jlab-enhanced-launcher/issues
Project-URL: Repository, https://github.com/jupyterlab-contrib/jlab-enhanced-launcher.git
Author: Frederic COLLONVAL
License: BSD 3-Clause License
License-File: LICENSE
Keywords: jupyter,jupyterlab,jupyterlab-extension
Classifier: Framework :: Jupyter
Classifier: Framework :: Jupyter :: JupyterLab
Classifier: Framework :: Jupyter :: JupyterLab :: 4
Classifier: Framework :: Jupyter :: JupyterLab :: Extensions
Classifier: Framework :: Jupyter :: JupyterLab :: Extensions :: Prebuilt
Classifier: License :: OSI Approved :: BSD License
Classifier: Programming Language :: Python
Classifier: Programming Language :: Python :: 3
Classifier: Programming Language :: Python :: 3.9
Classifier: Programming Language :: Python :: 3.10
Classifier: Programming Language :: Python :: 3.11
Classifier: Programming Language :: Python :: 3.12
Classifier: Programming Language :: Python :: 3.13
Requires-Python: >=3.9
